pyprimal/VERSION
pyprimal/__init__.py
pyprimal/core.py
pyprimal/libpath.py
pyprimal/model.py
pyprimal/lib/libpsm.dylib
pyprimal-0.0.0.dist-info/METADATA
pyprimal-0.0.0.dist-info/WHEEL
pyprimal-0.0.0.dist-info/top_level.txt
pyprimal-0.0.0.dist-info/RECORD
