Metadata-Version: 2.1
Name: pyprimal
Version: 0.0.0
Summary: PYthon package PaRametric sImplex Method for spArse Learning
Home-page: https://github.com/ShenQianli/primal
Author: Qianli Shen
Author-email: shenqianli@pku.edu.cn
Maintainer: Qianli Shen
Maintainer-email: shenqianli@pku.edu.cn
License: GPL-3.0
Platform: UNKNOWN
Classifier: Development Status :: 3 - Alpha
Classifier: Intended Audience :: Developers
Classifier: Intended Audience :: Science/Research
Classifier: Topic :: Scientific/Engineering :: Artificial Intelligence
Classifier: Topic :: Scientific/Engineering :: Mathematics
Classifier: Programming Language :: Python :: 3 :: Only
Classifier: License :: OSI Approved :: GNU General Public License v3 (GPLv3)
Requires-Dist: numpy
